{
  "common": {
    "name": "unifi-protect-tomatenforever",
    "version": "0.0.2",
    "news": {
      "0.0.2": {
        "en": "Initial release",
        "de": "Initiales release"
      }
    },
    "titleLang": {
      "en": "UniFi Protect Tomatenforever",
      "de": "UniFi Protect Tomatenforever"
    },
    "desc": {
      "en": "unifi-protect-tomatenforever",
      "de": "unifi-protect-tomatenforever"
    },
    "authors": [
      "Peter Baumert <ioBroker.unifi-protect@outlook.com>",
      "mcm1957 <mcm57@gmx.at>"
    ],
    "keywords": [
      "unifi-protect",
      "camera",
      "camera-security",
      "Ubiquiti"
    ],
    "licenseInformation": {
      "license": "MIT",
      "type": "free"
    },
    "platform": "Javascript/Node.js",
    "icon": "unifi-protect.png",
    "enabled": true,
    "extIcon": "https://raw.githubusercontent.com/iobroker-community-adapters/ioBroker.unifi-protect/master/admin/unifi-protect.png",
    "readme": "https://github.com/iobroker-community-adapters/ioBroker.unifi-protect/blob/master/README.md",
    "loglevel": "info",
    "tier": 2,
    "messagebox": true,
    "mode": "daemon",
    "type": "alarm",
    "compact": true,
    "connectionType": "local",
    "dataSource": "poll",
    "materialize": true,
    "dependencies": [
      {
        "js-controller": ">=5.0.0"
      }
    ]
  },
  "encryptedNative": [
    "password"
  ],
  "protectedNative": [
    "password"
  ],
  "native": {
    "protectip": "127.0.0.1",
    "protectport": 7443,
    "username": "admin",
    "password": "",
    "getMotions": false,
    "numMotions": 10,
    "secMotions": 600,
    "interval": 60,
    "wsCheck": 15,
    "motionTypes": {
      "motion": true,
      "smartDetectZone": false,
      "ring": false
    },
    "statesFilter": {
      "cameras": [
        "channels.enabled",
        "channels.name",
        "channels.rtspAlias",
        "channels.width",
        "connectedSince",
        "connectionHost",
        "firmwareVersion",
        "host",
        "isConnected",
        "isMotionDetected",
        "name",
        "state",
        "lastMotion",
        "lastMotion.start",
        "lastMotion.end",
        "lastMotion.type",
        "lastMotion.thumbnail",
        "lastMotion.heatmap"
      ],
      "motions": [
        "start",
        "end",
        "type",
        "thumbnail",
        "heatmap"
      ]
    },
    "downloadLastMotionThumb": false,
    "downloadLastMotionThumbWidth": 640,
    "takeSnapshotForLastMotion": false,
    "takeSnapshotForLastMotionWidth": 640,
    "takeSnapshotForLastMotionDelay": 0,
    "takeSnapshotManualWidth": 640
  },
  "objects": [],
  "instanceObjects": []
}
